{
  "blogs": [
    {
      "id": "1",
      "author": "Toby 1",
      "body": "body 1",
      "datetime": "datetime 1",
      "tags": [],
      "title": "title 1",
      "userId": "userId 1"
    },
    {
      "id": "2",
      "author": "author 2",
      "body": "body 2",
      "datetime": "datetime 2",
      "tags": [],
      "title": "title 2",
      "userId": "userId 2"
    },
    {
      "id": "3",
      "author": "author 3",
      "body": "body 3",
      "datetime": "datetime 3",
      "tags": [],
      "title": "title 3",
      "userId": "userId 3"
    },
    {
      "id": "4",
      "author": "author 4",
      "body": "body 4",
      "datetime": "datetime 4",
      "tags": [],
      "title": "title 4",
      "userId": "userId 4"
    }
  ]
}
